{"version":1.2,"people":[{"pose_keypoints_2d":[0,0,0,0,0,0,1.30001,53.0739,0.176614,1.29725,63.0614,0.198771,6.30202,69.829,0.284643,0,0,0,0,0,0,0,0,0,0,0,0,0,0,0,0,0,0,0,0,0,0,0,0,0,0,0,0,0,0,0,0,0,0,0,0,0,0,0,0,0,0,0,0,0,0,0,0,0,0,0,0,0,0,0,0,0,0,0,0],"face_keypoints_2d":[],"hand_left_keypoints_2d":[],"hand_right_keypoints_2d":[],"pose_keypoints_3d":[],"face_keypoints_3d":[],"hand_left_keypoints_3d":[],"hand_right_keypoints_3d":[]},{"pose_keypoints_2d":[0,0,0,0,0,0,0,0,0,0,0,0,0,0,0,0,0,0,0,0,0,0,0,0,0,0,0,0,0,0,0,0,0,0,0,0,1.30144,68.8706,0.101412,3.71271,78.8541,0.280663,1.29945,94.3477,0.219058,0,0,0,0,0,0,0,0,0,0,0,0,4.05767,97.2616,0.212453,4.36513,97.2356,0.212634,1.29882,96.2792,0.161261,0,0,0,0,0,0,0,0,0],"face_keypoints_2d":[],"hand_left_keypoints_2d":[],"hand_right_keypoints_2d":[],"pose_keypoints_3d":[],"face_keypoints_3d":[],"hand_left_keypoints_3d":[],"hand_right_keypoints_3d":[]}]}